csiphash24/__init__.py
csiphash24/_siphash.abi3.so
csiphash24-1.0.4.dist-info/METADATA
csiphash24-1.0.4.dist-info/RECORD
csiphash24-1.0.4.dist-info/WHEEL
csiphash24-1.0.4.dist-info/top_level.txt
