Metadata-Version: 2.1
Name: csiphash24
Version: 1.0.4
Summary: A CFFI-based implementation of SipHash24
Home-page: https://github.com/alexpirine/python-csiphash24
Author: Alexandre Syenchuk
Author-email: alex@pirine.fr
License: MIT
Platform: UNKNOWN
Classifier: Intended Audience :: Developers
Classifier: Programming Language :: Python :: 3.6
Requires-Python: >=3.6
Requires-Dist: cffi (>=1.4.0)
